example_wise_f1_maximizer/__init__.py
example_wise_f1_maximizer/meta_estimator.py
example_wise_f1_maximizer-0.1.5.dist-info/METADATA
example_wise_f1_maximizer-0.1.5.dist-info/WHEEL
example_wise_f1_maximizer-0.1.5.dist-info/top_level.txt
example_wise_f1_maximizer-0.1.5.dist-info/zip-safe
example_wise_f1_maximizer-0.1.5.dist-info/RECORD
