Metadata-Version: 2.1
Name: example-wise-f1-maximizer
Version: 0.1.5
Summary: A scikit-learn meta-estimator for multi-label classification that aims to maximize the example-wise F1 measure
Home-page: https://github.com/mrapp-ke/ExampleWiseF1Maximizer
Download-URL: https://github.com/mrapp-ke/ExampleWiseF1Maximizer/releases
Author: Michael Rapp
Author-email: michael.rapp.ml@gmail.com
License: MIT
Project-URL: Issue Tracker, https://github.com/mrapp-ke/ExampleWiseF1Maximizer/issues
Keywords: machine learning,scikit-learn,multi-label classification
Platform: any
Classifier: Development Status :: 5 - Production/Stable
Classifier: Intended Audience :: Science/Research
Classifier: License :: OSI Approved :: MIT License
Classifier: Programming Language :: Python :: 3
Classifier: Operating System :: OS Independent
Classifier: Topic :: Scientific/Engineering :: Artificial Intelligence
Classifier: Topic :: Software Development :: Libraries :: Python Modules
Requires-Python: >=3.7
Requires-Dist: numpy (<1.25,>=1.24)
Requires-Dist: scipy (<1.11,>=1.10)
Requires-Dist: scikit-learn (<1.3,>=1.2)
